reproducibility/__init__.py
reproducibility/scripts/__init__.py
reproducibility/scripts/conll.py
reproducibility/scripts/constants.py
reproducibility/scripts/genia.py
reproducibility/scripts/riqua.py
spacy_span_analyzer/__init__.py
spacy_span_analyzer/analyzer.py
spacy_span_analyzer/cli.py
spacy_span_analyzer-0.3.0.dist-info/LICENSE
spacy_span_analyzer-0.3.0.dist-info/METADATA
spacy_span_analyzer-0.3.0.dist-info/WHEEL
spacy_span_analyzer-0.3.0.dist-info/entry_points.txt
spacy_span_analyzer-0.3.0.dist-info/top_level.txt
spacy_span_analyzer-0.3.0.dist-info/RECORD
