Metadata-Version: 2.1
Name: spacy-span-analyzer
Version: 0.3.0
Summary: Analyze and characterize your Spans. Integrated with spaCy.
Home-page: https://github.com/ljvmiranda921/spacy-span-analyzer
Author: Lj V. Miranda
Author-email: ljvmiranda@gmail.com
License: UNKNOWN
Project-URL: Bug Tracker, https://github.com/ljvmiranda921/spacy-span-analyzer/issues
Platform: UNKNOWN
Classifier: Development Status :: 3 - Alpha
Classifier: Intended Audience :: Science/Research
Classifier: Intended Audience :: Developers
Classifier: Topic :: Scientific/Engineering
Classifier: Topic :: Scientific/Engineering :: Artificial Intelligence
Classifier: License :: OSI Approved :: MIT License
Requires-Python: >=3.6
License-File: LICENSE
Requires-Dist: spacy (>=3.1.0)
Requires-Dist: scipy
Requires-Dist: numpy
Requires-Dist: wasabi
Requires-Dist: typer
